svg_cartesian_plot/__init__.py
svg_cartesian_plot/base.py
svg_cartesian_plot/hemisphere.py
svg_cartesian_plot/inkscape.py
svg_cartesian_plot/optics.py
svg_cartesian_plot/scaling.py
svg_cartesian_plot/shapes.py
svg_cartesian_plot/svgcartesian.py
svg_cartesian_plot/version.py
svg_cartesian_plot/color/__init__.py
svg_cartesian_plot/color/_make_colormap_storage.py
svg_cartesian_plot/color/colormap_storage.py
svg_cartesian_plot/image/__init__.py
svg_cartesian_plot/text/__init__.py
svg_cartesian_plot-0.0.12.dist-info/licenses/LICENSE
svg_cartesian_plot-0.0.12.dist-info/METADATA
svg_cartesian_plot-0.0.12.dist-info/WHEEL
svg_cartesian_plot-0.0.12.dist-info/top_level.txt
svg_cartesian_plot-0.0.12.dist-info/RECORD
