Metadata-Version: 2.4
Name: svg_cartesian_plot
Version: 0.0.12
Summary: Make plots in scalable vector graphics
Home-page: https://github.com/cherenkov-plenoscope/svg_cartesian_plot
Author: Sebastian Achim Mueller
Author-email: sebastian-achim.mueller@mpi-hd.mpg.de
Classifier: Natural Language :: English
Classifier: Programming Language :: Python :: 3
Classifier: License :: OSI Approved :: MIT License
Classifier: Operating System :: OS Independent
Classifier: Topic :: Multimedia :: Graphics
Classifier: Intended Audience :: Science/Research
Requires-Python: >=3.0
License-File: LICENSE
Requires-Dist: svgwrite>=1.4.3
Requires-Dist: pillow>=10.2.0
Dynamic: author
Dynamic: author-email
Dynamic: classifier
Dynamic: description
Dynamic: description-content-type
Dynamic: home-page
Dynamic: license-file
Dynamic: requires-dist
Dynamic: requires-python
Dynamic: summary
